align_utils/__init__.py
align_utils/discovery.py
align_utils/exporters.py
align_utils/models.py
align_utils/py.typed
align_utils-1.5.0.dist-info/METADATA
align_utils-1.5.0.dist-info/WHEEL
align_utils-1.5.0.dist-info/RECORD
