Metadata-Version: 2.4
Name: align-utils
Version: 1.5.0
Summary: Utilities for parsing and processing align-system experiment data
Project-URL: Homepage, https://github.com/paulhax/align-tools
Project-URL: Repository, https://github.com/paulhax/align-tools
Project-URL: Issues, https://github.com/paulhax/align-tools/issues
Author: PaulHax
License: Apache-2.0
Keywords: align,data-processing,parsing,utilities
Classifier: Development Status :: 4 - Beta
Classifier: Intended Audience :: Developers
Classifier: License :: OSI Approved :: Apache Software License
Classifier: Programming Language :: Python :: 3
Classifier: Programming Language :: Python :: 3.9
Classifier: Programming Language :: Python :: 3.10
Classifier: Programming Language :: Python :: 3.11
Classifier: Programming Language :: Python :: 3.12
Requires-Python: >=3.10
Requires-Dist: pydantic>=2.0
Requires-Dist: pyyaml>=6.0
Provides-Extra: test
Requires-Dist: pytest>=7.0; extra == 'test'
